AUTHORS.rst
CHANGELOG.rst
CONTRIBUTING.rst
LICENSE
MANIFEST.in
README.rst
setup.cfg
setup.py
docs/Makefile
docs/api_reference.rst
docs/authors.rst
docs/changelog.rst
docs/conf.py
docs/contributing.rst
docs/index.rst
docs/license.rst
docs/make.bat
docs/recipes.rst
docs/requirements.txt
docs/_static/marshmallow-sqlalchemy-logo.png
docs/_templates/useful-links.html
docs/_templates/_templates/useful-links.html
marshmallow_sqlalchemy/__init__.py
marshmallow_sqlalchemy/convert.py
marshmallow_sqlalchemy/exceptions.py
marshmallow_sqlalchemy/fields.py
marshmallow_sqlalchemy/schema.py
marshmallow_sqlalchemy_pk.egg-info/PKG-INFO
marshmallow_sqlalchemy_pk.egg-info/SOURCES.txt
marshmallow_sqlalchemy_pk.egg-info/dependency_links.txt
marshmallow_sqlalchemy_pk.egg-info/not-zip-safe
marshmallow_sqlalchemy_pk.egg-info/requires.txt
marshmallow_sqlalchemy_pk.egg-info/top_level.txt
tests/__init__.py
tests/test_marshmallow_sqlalchemy.py