Metadata-Version: 1.1
Name: marshmallow-sqlalchemy-pk
Version: 0.13.2
Summary: SQLAlchemy integration with the marshmallow (de)serialization library
Home-page: https://github.com/tispratik/marshmallow-sqlalchemy
Author: Steven Loria
Author-email: sloria1@gmail.com
License: MIT
Keywords: sqlalchemy marshmallow
Platform: UNKNOWN
Classifier: Intended Audience :: Developers
Classifier: License :: OSI Approved :: MIT License
Classifier: Natural Language :: English
Classifier: Programming Language :: Python :: 2
Classifier: Programming Language :: Python :: 2.7
Classifier: Programming Language :: Python :: 3
Classifier: Programming Language :: Python :: 3.4
Classifier: Programming Language :: Python :: 3.5
Classifier: Programming Language :: Python :: 3.6
